audio_offset_finder/__init__.py
audio_offset_finder/audio_offset_finder.py
audio_offset_finder/cli.py
tests/__init__.py
tests/audio_offset_finder_test.py
tests/tool_test.py
audio_offset_finder-0.5.5.dist-info/AUTHORS
audio_offset_finder-0.5.5.dist-info/COPYING
audio_offset_finder-0.5.5.dist-info/METADATA
audio_offset_finder-0.5.5.dist-info/WHEEL
audio_offset_finder-0.5.5.dist-info/entry_points.txt
audio_offset_finder-0.5.5.dist-info/top_level.txt
audio_offset_finder-0.5.5.dist-info/RECORD
