Metadata-Version: 2.1
Name: audio-offset-finder
Version: 0.5.5
Summary: Find the offset of an audio file within another audio file
Home-page: https://github.com/bbcrd/audio-offset-finder
Author: Yves Raimond, Stephen Jolly, Chris Needham
Author-email: stephen.jolly@rd.bbc.co.uk
License: Apache License 2.0
Classifier: License :: OSI Approved :: Apache Software License
Classifier: Programming Language :: Python :: 3
License-File: COPYING
License-File: AUTHORS
Requires-Dist: librosa >=0.10.2
Requires-Dist: matplotlib >=3.7.3
Requires-Dist: numpy <2,>=1.22.3
Requires-Dist: scipy >=1.10.0
Provides-Extra: dev
Requires-Dist: black >=22.3.0 ; extra == 'dev'
Provides-Extra: test
Requires-Dist: pytest >=6.2.5 ; extra == 'test'
